django_session_jwt/__init__.py
django_session_jwt/admin.py
django_session_jwt/apps.py
django_session_jwt/models.py
django_session_jwt/settings.py
django_session_jwt/test.py
django_session_jwt/tests.py
django_session_jwt/urls.py
django_session_jwt/version.py
django_session_jwt/views.py
django_session_jwt/wsgi.py
django_session_jwt/middleware/__init__.py
django_session_jwt/middleware/session.py
django_session_jwt/migrations/__init__.py
django_session_jwt-0.10.19.dist-info/LICENSE
django_session_jwt-0.10.19.dist-info/METADATA
django_session_jwt-0.10.19.dist-info/WHEEL
django_session_jwt-0.10.19.dist-info/top_level.txt
django_session_jwt-0.10.19.dist-info/RECORD
