Metadata-Version: 2.1
Name: django-session-jwt
Version: 0.10.19
Summary: A django application that combines django.contrib.sessions with JWT.
Home-page: http://github.com/smartfile/django-session-jwt/
Author: SmartFile
Author-email: team@smartfile.com
Maintainer: Ben Timby
Maintainer-email: btimby@smartfile.com
License: MIT
Classifier: Development Status :: 4 - Beta
Classifier: Intended Audience :: Developers
Classifier: Operating System :: OS Independent
Classifier: Programming Language :: Python :: 2
Classifier: Programming Language :: Python :: 3
Classifier: Topic :: Software Development :: Libraries :: Python Modules
License-File: LICENSE
Requires-Dist: pyjwt (>=2)
